snoopdroid/__init__.py
snoopdroid/acquisition.py
snoopdroid/constants.py
snoopdroid/koodous.py
snoopdroid/ui.py
snoopdroid/utils.py
snoopdroid/virustotal.py
snoopdroid/__pycache__/__init__.cpython-38.pyc
snoopdroid/__pycache__/acquisition.cpython-38.pyc
snoopdroid/__pycache__/constants.cpython-38.pyc
snoopdroid/__pycache__/koodous.cpython-38.pyc
snoopdroid/__pycache__/ui.cpython-38.pyc
snoopdroid/__pycache__/utils.cpython-38.pyc
snoopdroid/__pycache__/virustotal.cpython-38.pyc
snoopdroid/data/knowngood.txt
snoopdroid-2.3.data/scripts/snoopdroid
snoopdroid-2.3.dist-info/LICENSE
snoopdroid-2.3.dist-info/METADATA
snoopdroid-2.3.dist-info/WHEEL
snoopdroid-2.3.dist-info/top_level.txt
snoopdroid-2.3.dist-info/RECORD
