Metadata-Version: 2.1
Name: snoopdroid
Version: 2.3
Summary: Extract all apks from an Android device and check for malicious apps
Home-page: UNKNOWN
Author: Claudio Guarnieri
Author-email: nex@nex.sx
License: GPLv3
Keywords: security android
Platform: UNKNOWN
Classifier: Programming Language :: Python :: 3
Classifier: Topic :: Security
Classifier: License :: OSI Approved :: GNU General Public License v3 or later (GPLv3+)
Classifier: Operating System :: Android
Classifier: Operating System :: POSIX :: Linux
Classifier: Operating System :: MacOS
Classifier: Environment :: Console
Requires-Dist: adb
Requires-Dist: halo
Requires-Dist: requests
Requires-Dist: rsa
Requires-Dist: terminaltables
Requires-Dist: tqdm
